catfood/__init__.py
catfood/constant.py
catfood/py.typed
catfood/exceptions/__init__.py
catfood/exceptions/operation.py
catfood/exceptions/request.py
catfood/functions/__init__.py
catfood/functions/files.py
catfood/functions/print.py
catfood/functions/terminal.py
catfood/functions/format/__init__.py
catfood/functions/format/github.py
catfood/functions/github/__init__.py
catfood/functions/github/api.py
catfood/functions/github/token.py
catfood-1.0.7.dist-info/licenses/LICENSE
catfood-1.0.7.dist-info/METADATA
catfood-1.0.7.dist-info/WHEEL
catfood-1.0.7.dist-info/top_level.txt
catfood-1.0.7.dist-info/RECORD
