Metadata-Version: 2.4
Name: catfood
Version: 1.0.7
Summary: A collection of various commonly used functions. / 各种常用函数的集合。
Author: 鸭鸭「カモ」
License-Expression: Apache-2.0
Project-URL: Homepage, https://github.com/DuckDuckStudio/catfood
Project-URL: Repository, https://github.com/DuckDuckStudio/catfood
Project-URL: Issues, https://github.com/DuckDuckStudio/catfood/issues
Classifier: Development Status :: 3 - Alpha
Classifier: Environment :: Console
Classifier: Intended Audience :: Developers
Classifier: Natural Language :: Chinese (Simplified)
Classifier: Operating System :: OS Independent
Classifier: Programming Language :: Python
Classifier: Programming Language :: Python :: 3
Classifier: Programming Language :: Python :: 3.12
Classifier: Programming Language :: Python :: 3.13
Classifier: Programming Language :: Python :: 3.14
Classifier: Programming Language :: Python :: Implementation :: CPython
Classifier: Topic :: Software Development
Classifier: Topic :: Software Development :: Libraries
Classifier: Topic :: Software Development :: Libraries :: Python Modules
License-File: LICENSE
Requires-Dist: colorama>=0.4.6
Requires-Dist: requests>=2.32.5
Requires-Dist: keyring>=25.6.0
Requires-Dist: typing_extensions; python_version < "3.13"
Provides-Extra: typing-check
Requires-Dist: pyright; extra == "typing-check"
Provides-Extra: build-and-publish
Requires-Dist: build; extra == "build-and-publish"
Requires-Dist: twine; extra == "build-and-publish"
Dynamic: license-file
